htmldocx/__init__.py
htmldocx/h2d.py
html3docx-1.0.1.dist-info/LICENSE
html3docx-1.0.1.dist-info/METADATA
html3docx-1.0.1.dist-info/WHEEL
html3docx-1.0.1.dist-info/top_level.txt
html3docx-1.0.1.dist-info/RECORD
