Metadata-Version: 2.1
Name: html3docx
Version: 1.0.1
Summary: A fork of https://github.com/pqzx/html2docx.  This version will focus on expedient changes for our particular use case.
Author: John Jordan
License: MIT License
Project-URL: Homepage, https://github.com/johnjor/html2docx
License-File: LICENSE
